ImageClassifier/__init__.py
ImageClassifier/img.py
image_classifier-0.0.1.dist-info/LICENSE
image_classifier-0.0.1.dist-info/METADATA
image_classifier-0.0.1.dist-info/WHEEL
image_classifier-0.0.1.dist-info/top_level.txt
image_classifier-0.0.1.dist-info/RECORD
