Metadata-Version: 2.1
Name: image-classifier
Version: 0.0.1
Summary: Python package for creating Image classifiers
Home-page: https://github.com/pranav377/image-classifier
Author: Pranava Mohan
License: MIT
Platform: UNKNOWN
Classifier: Programming Language :: Python :: 3
Classifier: License :: OSI Approved :: MIT License
Classifier: Operating System :: OS Independent
Requires-Python: >=3.6
Requires-Dist: tensorflow
Requires-Dist: keras
Requires-Dist: sklearn
Requires-Dist: numpy
Requires-Dist: opencv-python
